revpicommander/__init__.py
revpicommander/__main__.py
revpicommander/aclmanager.py
revpicommander/avahisearch.py
revpicommander/backgroundworker.py
revpicommander/debugcontrol.py
revpicommander/debugios.py
revpicommander/helper.py
revpicommander/mqttmanager.py
revpicommander/oss_licenses.py
revpicommander/proginit.py
revpicommander/revpicommander.py
revpicommander/revpifiles.py
revpicommander/revpiinfo.py
revpicommander/revpilogfile.py
revpicommander/revpioption.py
revpicommander/revpiplclist.py
revpicommander/revpiprogram.py
revpicommander/simulator.py
revpicommander/sshauth.py
revpicommander/locale/revpicommander_de.qm
revpicommander/locale/revpicommander_en.qm
revpicommander/ssh_tunneling/__init__.py
revpicommander/ssh_tunneling/server.py
revpicommander/ui/__init__.py
revpicommander/ui/aclmanager_ui.py
revpicommander/ui/avahisearch_ui.py
revpicommander/ui/backgroundworker_ui.py
revpicommander/ui/debugcontrol_ui.py
revpicommander/ui/debugios_ui.py
revpicommander/ui/files_ui.py
revpicommander/ui/mqttmanager_ui.py
revpicommander/ui/oss_licenses_ui.py
revpicommander/ui/ressources_rc.py
revpicommander/ui/revpicommander_ui.py
revpicommander/ui/revpiinfo_ui.py
revpicommander/ui/revpilogfile_ui.py
revpicommander/ui/revpioption_ui.py
revpicommander/ui/revpiplclist_ui.py
revpicommander/ui/revpiprogram_ui.py
revpicommander/ui/simulator_ui.py
revpicommander/ui/sshauth_ui.py
revpicommander-0.11.0.dist-info/LICENSE.txt
revpicommander-0.11.0.dist-info/METADATA
revpicommander-0.11.0.dist-info/WHEEL
revpicommander-0.11.0.dist-info/entry_points.txt
revpicommander-0.11.0.dist-info/top_level.txt
revpicommander-0.11.0.dist-info/RECORD
