Metadata-Version: 2.1
Name: revpicommander
Version: 0.11.0
Summary: GUI for Revolution Pi to upload programs and do IO-Checks
Home-page: https://revpimodio.org/revpipyplc/
Author: Sven Sager
Author-email: akira@narux.de
Maintainer: Sven Sager
Maintainer-email: akira@revpimodio.org
License: GPLv2
Keywords: revpi,revolution pi,revpimodio,plc
Platform: all
Classifier: License :: OSI Approved :: GNU General Public License v2 (GPLv2)
License-File: LICENSE.txt
Requires-Dist: keyring
Requires-Dist: PyQt5
Requires-Dist: paramiko
Requires-Dist: revpimodio2
Requires-Dist: zeroconf
